sutowebdav/__init__.py
sutowebdav/client.py
sutowebdav-0.2.1.dist-info/LICENSE
sutowebdav-0.2.1.dist-info/METADATA
sutowebdav-0.2.1.dist-info/WHEEL
sutowebdav-0.2.1.dist-info/RECORD
