Metadata-Version: 2.1
Name: sutowebdav
Version: 0.2.1
Summary: A simple asynchronous WebDAV client in Python.
Author: hsn
Author-email: hsn1919810@gmail.com
Requires-Python: >=3.11,<4.0
Classifier: Programming Language :: Python :: 3
Classifier: Programming Language :: Python :: 3.11
Classifier: Programming Language :: Python :: 3.12
Requires-Dist: httpx (>=0.27.2,<0.28.0)
